baselog/__init__.py
baselog/baselog.py
baselog/py.typed
baselog-2.1.0.dist-info/LICENSE
baselog-2.1.0.dist-info/METADATA
baselog-2.1.0.dist-info/WHEEL
baselog-2.1.0.dist-info/top_level.txt
baselog-2.1.0.dist-info/RECORD
