Metadata-Version: 2.2
Name: baselog
Version: 2.1.0
Summary: helper for log initialization
Author-email: Ben Burke <actualben@users.noreply.github.com>
Project-URL: Homepage, https://github.com/edencehealth/baselog
Project-URL: Bug Tracker, https://github.com/edencehealth/baselog/issues
Classifier: Programming Language :: Python :: 3
Classifier: License :: OSI Approved :: GNU Lesser General Public License v2 (LGPLv2)
Classifier: Operating System :: OS Independent
Requires-Python: >=3.10
License-File: LICENSE
